PACKET_PARSER/register_router.v
module register_router(clk,reset,pkt_valid,data_in,fifo_full,rst_int_reg,detect_add,
                       ld_state,laf_state,full_state,lfd_state,
                       parity_done,low_pkt_valid,error,dout);

// declaring the regs and wires

input clk,reset,pkt_valid,fifo_full,rst_int_reg,detect_add,ld_state,laf_state,
      full_state,lfd_state;

input [7:0] data_in;

output reg error,low_pkt_valid,parity_done;
output reg [7:0] dout;


// creating 4 internal register for header byte storing,internal parity
// byte,packet parity byte,fifo full state byte each are 8 bits bcz all are bytes

reg [7:0] header_byte,internal_parity_byte,packet_parity_byte,fifo_full_state_byte;


// writing logic for header byte storing
// header store add detect address and present state at load first data and
// pkt valid is high and correct address destination

always@(posedge clk)
begin
    if(!reset)
        header_byte<=0;
    else if(pkt_valid && detect_add && (data_in[1:0] != 2'd3))
        header_byte<=data_in;
end



// logic for fifo full state byte
// storing the data in after full state

always@(posedge clk)
begin
    if(!reset)
        fifo_full_state_byte <= 0;
    else if(ld_state && fifo_full)
        fifo_full_state_byte <= data_in;
    else if(detect_add)
        fifo_full_state_byte <= 0;
    else
        fifo_full_state_byte <= fifo_full_state_byte ;
end



// writing logic for dout
// data out is works only at play load data in header data without error

always@(posedge clk)
begin
    if(!reset)
        dout<=0;

    else if(detect_add && pkt_valid && (data_in[1:0] != 2'd3))
        dout <= dout;

    else if(lfd_state)
        dout<=header_byte;

    else if(ld_state &&(!fifo_full))
        dout<=data_in;

    else if(full_state)
        dout<=dout;

    else if(laf_state)
        dout<=fifo_full_state_byte;

    else
        dout<=dout;
end



// writing logic for internal parity
// first it is ex or operation with header byte and then after continous ex or
// with each payload data stored into internal parity

always@(posedge clk)
begin
    if(!reset)
        internal_parity_byte<=0;

    else if(detect_add)
        internal_parity_byte<=0;

    else if(lfd_state)
        internal_parity_byte <= internal_parity_byte ^ header_byte;

    else if(ld_state && (!fifo_full))
        internal_parity_byte <= internal_parity_byte ^ data_in;

    else
        internal_parity_byte <= internal_parity_byte;
end



// writing logic for packet parity
// packet parity check weather state is parity_data only in this state
// only we getting parity of packets

always@(posedge clk)
begin
    if(!reset)
        packet_parity_byte <= 0;

    else if(detect_add)
        packet_parity_byte <= 0;

    else if((ld_state && (!pkt_valid)) && (!fifo_full))
        packet_parity_byte <= data_in;

    else if(!pkt_valid && rst_int_reg)
        packet_parity_byte<=0;

    else
        packet_parity_byte <= packet_parity_byte;
end



// parity done logic

always@(posedge clk)
begin
    if(!reset)
        parity_done <= 1'b0;

    else if(ld_state && (!pkt_valid) && (!fifo_full))
        parity_done <= 1'b1;

    else if(laf_state && (!parity_done) && low_pkt_valid)
        parity_done <= 1'b1;

    else
        parity_done <= 1'b0;
end



// error logic

always@(posedge clk)
begin
    if(!reset)
        error <=1'b0;

    else if((packet_parity_byte != internal_parity_byte) && parity_done)
        error <=1'b1;

    else if((packet_parity_byte == internal_parity_byte) && parity_done)
        error <=1'b0;

    else
        error <= 0;
end



// low_packet_valid logic this means if ther is no packets packet goes low so
// this is negation of pkt valid

always@(*)
begin
    if(!reset)
        low_pkt_valid <=0;

    else if(parity_done)
        low_pkt_valid <=1'b1;

    else if(pkt_valid)
        low_pkt_valid <=1'b0;

    else
        low_pkt_valid <=1'b1;
end

endmodule

PACKET_PARSER/tb_register_router.v
`timescale 1ns/1ps

module tb_register_router;

reg clk;
reg reset;
reg pkt_valid;
reg fifo_full;
reg rst_int_reg;
reg detect_add;
reg ld_state;
reg laf_state;
reg full_state;
reg lfd_state;

reg [7:0] data_in;

wire parity_done;
wire low_pkt_valid;
wire error;
wire [7:0] dout;


// DUT

register_router DUT(
clk,reset,pkt_valid,data_in,fifo_full,rst_int_reg,detect_add,
ld_state,laf_state,full_state,lfd_state,
parity_done,low_pkt_valid,error,dout
);


// clock generation

always #5 clk = ~clk;


// dump file for GTKWave

initial
begin
$dumpfile("router_register.vcd");
$dumpvars(0,tb_register_router);
end


initial
begin

$display("==== Router Register Testbench Started ====");

clk = 0;
reset = 0;
pkt_valid = 0;
fifo_full = 0;
rst_int_reg = 0;
detect_add = 0;
ld_state = 0;
laf_state = 0;
full_state = 0;
lfd_state = 0;
data_in = 0;


//------------------------------------------------
// TEST 1 : RESET
//------------------------------------------------

#10
reset = 1;
$display("RESET RELEASED");


//------------------------------------------------
// TEST 2 : HEADER WRITE
//------------------------------------------------

#10
pkt_valid = 1;
detect_add = 1;
lfd_state = 1;

data_in = 8'h14;   // header

#10
detect_add = 0;
lfd_state = 0;


//------------------------------------------------
// TEST 3 : PAYLOAD DATA
//------------------------------------------------

ld_state = 1;

data_in = 8'h11;
#10

data_in = 8'h22;
#10

data_in = 8'h33;
#10

//------------------------------------------------
// TEST 4 : PARITY BYTE
//------------------------------------------------

pkt_valid = 0;
data_in = 8'h44;

#10


//------------------------------------------------
// TEST 5 : FIFO FULL CONDITION
//------------------------------------------------

pkt_valid = 1;
fifo_full = 1;
ld_state = 1;

data_in = 8'hAA;

#10

fifo_full = 0;


//------------------------------------------------
// TEST 6 : LAF STATE
//------------------------------------------------

laf_state = 1;

#10

laf_state = 0;


//------------------------------------------------
// TEST 7 : ERROR CHECK
//------------------------------------------------

pkt_valid = 1;
detect_add = 1;

data_in = 8'h23;

#10

detect_add = 0;

ld_state = 1;

data_in = 8'h45;
#10

pkt_valid = 0;
data_in = 8'h99; // wrong parity

#20


//------------------------------------------------

$display("==== TESTBENCH FINISHED ====");

#20
$finish;

end

endmodule

PACKET_PARSER/router_register.vcd
$date
	Fri Mar 06 11:59:52 2026
$end
$version
	Icarus Verilog
$end
$timescale
	1ps
$end
$scope module tb_register_router $end
$var wire 1 ! parity_done $end
$var wire 1 " low_pkt_valid $end
$var wire 1 # error $end
$var wire 8 $ dout [7:0] $end
$var reg 1 % clk $end
$var reg 8 & data_in [7:0] $end
$var reg 1 ' detect_add $end
$var reg 1 ( fifo_full $end
$var reg 1 ) full_state $end
$var reg 1 * laf_state $end
$var reg 1 + ld_state $end
$var reg 1 , lfd_state $end
$var reg 1 - pkt_valid $end
$var reg 1 . reset $end
$var reg 1 / rst_int_reg $end
$scope module DUT $end
$var wire 1 % clk $end
$var wire 8 0 data_in [7:0] $end
$var wire 1 ' detect_add $end
$var wire 1 ( fifo_full $end
$var wire 1 ) full_state $end
$var wire 1 * laf_state $end
$var wire 1 + ld_state $end
$var wire 1 , lfd_state $end
$var wire 1 - pkt_valid $end
$var wire 1 . reset $end
$var wire 1 / rst_int_reg $end
$var reg 8 1 dout [7:0] $end
$var reg 1 # error $end
$var reg 8 2 fifo_full_state_byte [7:0] $end
$var reg 8 3 header_byte [7:0] $end
$var reg 8 4 internal_parity_byte [7:0] $end
$var reg 1 " low_pkt_valid $end
$var reg 8 5 packet_parity_byte [7:0] $end
$var reg 1 ! parity_done $end
$upscope $end
$upscope $end
$enddefinitions $end
$comment Show the parameter values. $end
$dumpall
$end
#0
$dumpvars
bx 5
bx 4
bx 3
bx 2
bx 1
b0 0
0/
0.
0-
0,
0+
0*
0)
0(
0'
b0 &
0%
bx $
x#
0"
x!
$end
#5000
b0 3
b0 2
b0 $
b0 1
b0 4
b0 5
0!
0#
1%
#10000
1"
0%
1.
#15000
1%
#20000
0"
0%
b10100 &
b10100 0
1,
1'
1-
#25000
b10100 3
1%
#30000
0%
b10001 &
b10001 0
1+
0,
0'
#35000
b10001 4
b10001 $
b10001 1
1%
#40000
0%
b100010 &
b100010 0
#45000
b100010 $
b100010 1
b110011 4
1%
#50000
0%
b110011 &
b110011 0
#55000
b0 4
b110011 $
b110011 1
1%
#60000
1"
0%
b1000100 &
b1000100 0
0-
#65000
b1000100 $
b1000100 1
b1000100 4
b1000100 5
1!
1%
#70000
0%
b10101010 &
b10101010 0
1(
1-
#75000
0"
0!
b10101010 2
1%
#80000
0%
1*
0(
#85000
b10101010 $
b10101010 1
b11101110 4
1%
#90000
0%
b100011 &
b100011 0
1'
0*
#95000
b0 5
b0 4
b100011 $
b100011 1
b0 2
1%
#100000
0%
b1000101 &
b1000101 0
0'
#105000
b1000101 $
b1000101 1
b1000101 4
1%
#110000
1"
0%
b10011001 &
b10011001 0
0-
#115000
1!
b10011001 5
b11011100 4
b10011001 $
b10011001 1
1%
#120000
0%
#125000
b1000101 4
1#
1%
#130000
0%
#135000
b11011100 4
1%
#140000
0%
#145000
b1000101 4
1%
