FIFO/fifo_16x9.v
module fifo_16x9_router(
    input clk,
    input reset,
    input write_enb,
    input read_enb,
    input soft_reset,
    input lfd_state,
    input [7:0] data_in,
    output full,
    output empty,
    output reg [7:0] data_out
);

// internal signals
reg [4:0] write_addr, read_addr;
reg [8:0] mem [0:15];
reg [6:0] fifo_down_counter;
reg lfd_state_temp;

integer i;

// delay lfd_state by one clock
always @(posedge clk)
begin
    if(!reset)
        lfd_state_temp <= 0;
    else
        lfd_state_temp <= lfd_state;
end

//----------------------------------
// WRITE OPERATION
//----------------------------------

always @(posedge clk)
begin
    if(!reset)
    begin
        for(i=0;i<16;i=i+1)
            mem[i] <= 0;
        write_addr <= 0;
    end

    else if(soft_reset)
    begin
        for(i=0;i<16;i=i+1)
            mem[i] <= 0;
        write_addr <= 0;
    end

    else if(write_enb && !full)
    begin
        mem[write_addr[3:0]] <= {lfd_state_temp,data_in};
        write_addr <= write_addr + 1;
    end
end

//----------------------------------
// READ OPERATION
//----------------------------------

always @(posedge clk)
begin
    if(!reset)
    begin
        data_out <= 0;
        read_addr <= 0;
    end

    else if(soft_reset)
    begin
        data_out <= 8'bz;
        read_addr <= 0;
    end

    else if(fifo_down_counter == 0 && data_out != 8'b0)
    begin
        data_out <= 8'bz;
    end

    else if(read_enb && !empty)
    begin
        data_out <= mem[read_addr[3:0]][7:0];
        read_addr <= read_addr + 1;
    end
end

//----------------------------------
// FIFO DOWN COUNTER LOGIC
//----------------------------------

always @(posedge clk)
begin
    if(!reset)
        fifo_down_counter <= 0;

    else if(soft_reset)
        fifo_down_counter <= 0;

    else if(read_enb && !empty)
    begin
        if(mem[read_addr[3:0]][8] == 1'b1)
            fifo_down_counter <= mem[read_addr[3:0]][7:2] + 1;

        else if(fifo_down_counter != 0)
            fifo_down_counter <= fifo_down_counter - 1;
    end
end

//----------------------------------
// FIFO FULL LOGIC
//----------------------------------

assign full = ((write_addr[3:0] == read_addr[3:0]) &&
              (write_addr[4] != read_addr[4])) ? 1'b1 : 1'b0;

//----------------------------------
// FIFO EMPTY LOGIC
//----------------------------------

assign empty = ((write_addr[3:0] == read_addr[3:0]) &&
               (write_addr[4] == read_addr[4])) ? 1'b1 : 1'b0;

endmodule

FIFO/tb_fifo_16x9_router.v
`timescale 1ns/1ps

module tb_fifo_16x9_router;

reg clk;
reg reset;
reg write_enb;
reg read_enb;
reg soft_reset;
reg lfd_state;
reg [7:0] data_in;

wire full;
wire empty;
wire [7:0] data_out;

integer i;

// DUT
fifo_16x9_router dut(
    .clk(clk),
    .reset(reset),
    .write_enb(write_enb),
    .read_enb(read_enb),
    .soft_reset(soft_reset),
    .lfd_state(lfd_state),
    .data_in(data_in),
    .full(full),
    .empty(empty),
    .data_out(data_out)
);

// clock generation
always #5 clk = ~clk;

initial begin
    $dumpfile("fifo_router.vcd");
    $dumpvars(0,tb_fifo_16x9_router);
end

//--------------------------------------------------
// TEST SEQUENCE
//--------------------------------------------------

initial begin

$display("=====================================");
$display("Starting FIFO Router Testbench");
$display("=====================================");

clk = 0;
reset = 0;
write_enb = 0;
read_enb = 0;
soft_reset = 0;
lfd_state = 0;
data_in = 0;

#20
reset = 1;

$display("RESET RELEASED");

//------------------------------------
// TEST 1 : SIMPLE PACKET WRITE
//------------------------------------

$display("TEST1 : Write packet");

lfd_state = 1;
write_enb = 1;
data_in = 8'b00010100; // header
#10

lfd_state = 0;
data_in = 8'h11;
#10

data_in = 8'h22;
#10

data_in = 8'h33;
#10

data_in = 8'h44; // parity
#10

write_enb = 0;


//------------------------------------
// TEST 2 : READ PACKET
//------------------------------------

$display("TEST2 : Read packet");

#20
read_enb = 1;

repeat(5) #10;

read_enb = 0;


//------------------------------------
// TEST 3 : FIFO FULL CONDITION
//------------------------------------

$display("TEST3 : Fill FIFO to FULL");

write_enb = 1;

for(i=0;i<16;i=i+1) begin
    data_in = i;
    #10;
end

write_enb = 0;

if(full)
    $display("FIFO FULL detected correctly");
else
    $display("ERROR : FULL not detected");


//------------------------------------
// TEST 4 : FIFO EMPTY CONDITION
//------------------------------------

$display("TEST4 : Empty FIFO");

read_enb = 1;

for(i=0;i<16;i=i+1)
    #10;

read_enb = 0;

if(empty)
    $display("FIFO EMPTY detected correctly");
else
    $display("ERROR : EMPTY not detected");


//------------------------------------
// TEST 5 : WRITE WHEN FULL
//------------------------------------

$display("TEST5 : Write when FIFO FULL");

write_enb = 1;
data_in = 8'hAA;
#10
write_enb = 0;


//------------------------------------
// TEST 6 : READ WHEN EMPTY
//------------------------------------

$display("TEST6 : Read when FIFO EMPTY");

read_enb = 1;
#10
read_enb = 0;


//------------------------------------
// TEST 7 : SOFT RESET
//------------------------------------

$display("TEST7 : Soft Reset");

write_enb = 1;
data_in = 8'h55;
#10

soft_reset = 1;
#10

soft_reset = 0;
write_enb = 0;


//------------------------------------
// TEST COMPLETE
//------------------------------------

#50

$display("=====================================");
$display("TESTBENCH COMPLETE");
$display("=====================================");

$finish;

end

endmodule

FIFO/fifo_router.vcd
$date
	Fri Mar 06 10:41:55 2026
$end
$version
	Icarus Verilog
$end
$timescale
	1ps
$end
$scope module tb_fifo_16x9_router $end
$var wire 1 ! full $end
$var wire 1 " empty $end
$var wire 8 # data_out [7:0] $end
$var reg 1 $ clk $end
$var reg 8 % data_in [7:0] $end
$var reg 1 & lfd_state $end
$var reg 1 ' read_enb $end
$var reg 1 ( reset $end
$var reg 1 ) soft_reset $end
$var reg 1 * write_enb $end
$var integer 32 + i [31:0] $end
$scope module dut $end
$var wire 1 $ clk $end
$var wire 8 , data_in [7:0] $end
$var wire 1 & lfd_state $end
$var wire 1 ' read_enb $end
$var wire 1 ( reset $end
$var wire 1 ) soft_reset $end
$var wire 1 * write_enb $end
$var wire 1 ! full $end
$var wire 1 " empty $end
$var reg 8 - data_out [7:0] $end
$var reg 7 . fifo_down_counter [6:0] $end
$var reg 1 / lfd_state_temp $end
$var reg 5 0 read_addr [4:0] $end
$var reg 5 1 write_addr [4:0] $end
$var integer 32 2 i [31:0] $end
$upscope $end
$upscope $end
$enddefinitions $end
$comment Show the parameter values. $end
$dumpall
$end
#0
$dumpvars
bx 2
bx 1
bx 0
x/
bx .
bx -
b0 ,
bx +
0*
0)
0(
0'
0&
b0 %
0$
bx #
x"
x!
$end
#5000
0!
1"
0/
b0 1
b0 0
b0 #
b0 -
b0 .
b10000 2
1$
#10000
0$
#15000
b10000 2
1$
#20000
0$
b10100 %
b10100 ,
1*
1&
1(
#25000
0"
1/
b1 1
1$
#30000
0$
b10001 %
b10001 ,
0&
#35000
b10 1
0/
1$
#40000
0$
b100010 %
b100010 ,
#45000
b11 1
1$
#50000
0$
b110011 %
b110011 ,
#55000
b100 1
1$
#60000
0$
b1000100 %
b1000100 ,
#65000
b101 1
1$
#70000
0$
0*
#75000
1$
#80000
0$
#85000
1$
#90000
0$
1'
#95000
b1 0
b10100 #
b10100 -
1$
#100000
0$
#105000
bz #
bz -
b101 .
1$
#110000
0$
#115000
b10 0
b10001 #
b10001 -
1$
#120000
0$
#125000
b11 0
b100010 #
b100010 -
b100 .
1$
#130000
0$
#135000
b11 .
b100 0
b110011 #
b110011 -
1$
#140000
0$
b0 %
b0 ,
b0 +
1*
0'
#145000
b110 1
1$
#150000
0$
b1 %
b1 ,
b1 +
#155000
b111 1
1$
#160000
0$
b10 %
b10 ,
b10 +
#165000
b1000 1
1$
#170000
0$
b11 %
b11 ,
b11 +
#175000
b1001 1
1$
#180000
0$
b100 %
b100 ,
b100 +
#185000
b1010 1
1$
#190000
0$
b101 %
b101 ,
b101 +
#195000
b1011 1
1$
#200000
0$
b110 %
b110 ,
b110 +
#205000
b1100 1
1$
#210000
0$
b111 %
b111 ,
b111 +
#215000
b1101 1
1$
#220000
0$
b1000 %
b1000 ,
b1000 +
#225000
b1110 1
1$
#230000
0$
b1001 %
b1001 ,
b1001 +
#235000
b1111 1
1$
#240000
0$
b1010 %
b1010 ,
b1010 +
#245000
b10000 1
1$
#250000
0$
b1011 %
b1011 ,
b1011 +
#255000
b10001 1
1$
#260000
0$
b1100 %
b1100 ,
b1100 +
#265000
b10010 1
1$
#270000
0$
b1101 %
b1101 ,
b1101 +
#275000
b10011 1
1$
#280000
0$
b1110 %
b1110 ,
b1110 +
#285000
1!
b10100 1
1$
#290000
0$
b1111 %
b1111 ,
b1111 +
#295000
1$
#300000
0$
1'
0*
b0 +
#305000
0!
b101 0
b1000100 #
b1000100 -
b10 .
1$
#310000
0$
b1 +
#315000
b1 .
b110 0
b0 #
b0 -
1$
#320000
0$
b10 +
#325000
b111 0
b1 #
b1 -
b0 .
1$
#330000
0$
b11 +
#335000
bz #
bz -
1$
#340000
0$
b100 +
#345000
b1000 0
b10 #
b10 -
1$
#350000
0$
b101 +
#355000
bz #
bz -
1$
#360000
0$
b110 +
#365000
b1001 0
b11 #
b11 -
1$
#370000
0$
b111 +
#375000
bz #
bz -
1$
#380000
0$
b1000 +
#385000
b1010 0
b100 #
b100 -
1$
#390000
0$
b1001 +
#395000
bz #
bz -
1$
#400000
0$
b1010 +
#405000
b1011 0
b101 #
b101 -
1$
#410000
0$
b1011 +
#415000
bz #
bz -
1$
#420000
0$
b1100 +
#425000
b1100 0
b110 #
b110 -
1$
#430000
0$
b1101 +
#435000
bz #
bz -
1$
#440000
0$
b1110 +
#445000
b1101 0
b111 #
b111 -
1$
#450000
0$
b1111 +
#455000
bz #
bz -
1$
#460000
0$
b10101010 %
b10101010 ,
1*
0'
b10000 +
#465000
b10101 1
1$
#470000
0$
1'
0*
#475000
b1110 0
b1000 #
b1000 -
1$
#480000
0$
b1010101 %
b1010101 ,
1*
0'
#485000
b10110 1
bz #
bz -
1$
#490000
0$
1)
#495000
1"
b0 0
b0 1
b10000 2
1$
#500000
0$
0*
0)
