SYNCHRONIZER/synchronizer_router.v
module synchronizer_router(detect_add,data_in,write_enb_reg,clk,reset,
vld_out_0,vld_out_1,vld_out_2,read_enb_0,read_enb_1,read_enb_2,
write_enb,fifo_full,empty_0,empty_1,empty_2,
soft_reset_0,soft_reset_1,soft_reset_2,full_0,full_1,full_2);

// declaring the input and output ports

input detect_add,write_enb_reg,clk,reset,read_enb_0,read_enb_1,read_enb_2,
      empty_0,empty_1,empty_2,full_0,full_1,full_2;

input [1:0] data_in;

output vld_out_0,vld_out_1,vld_out_2;
output reg [2:0] write_enb;
output reg fifo_full;
output reg soft_reset_0,soft_reset_1,soft_reset_2;

// creating the internal register

reg [1:0] addr_data;
reg [6:0] out_fifo_0_counter;
reg [6:0] out_fifo_1_counter;
reg [6:0] out_fifo_2_counter;


// storing detecting the destination_address_signal

always @(posedge clk)
begin
    if(!reset)
        addr_data <= 0;
    else if(detect_add)
        addr_data <= data_in;
end


// destination address decoding and sending write_enb signal

always @(*)
begin
    if(!reset)
        write_enb = 0;
    else
    begin
        if(write_enb_reg)
        begin
            case(addr_data)
                2'b00: write_enb = 3'b001;
                2'b01: write_enb = 3'b010;
                2'b10: write_enb = 3'b100;
                default: write_enb = 3'b000;
            endcase
        end
        else
            write_enb = 3'b000;
    end
end


// fifo full signal asserted based on full status of each fifo

always @(*)
begin
    if(!reset)
        fifo_full = 0;
    else
    begin
        case(addr_data)
            2'b00: fifo_full = full_0;
            2'b01: fifo_full = full_1;
            2'b10: fifo_full = full_2;
            default: fifo_full = 0;
        endcase
    end
end


// valid output signal generation

assign vld_out_0 = ~empty_0;
assign vld_out_1 = ~empty_1;
assign vld_out_2 = ~empty_2;


// soft reset signal generation for each fifo

wire count_0 = (out_fifo_0_counter == 6'd29) ? 1'b1 : 1'b0;
wire count_1 = (out_fifo_1_counter == 6'd29) ? 1'b1 : 1'b0;
wire count_2 = (out_fifo_2_counter == 6'd29) ? 1'b1 : 1'b0;


// FIFO 0 counter logic

always @(posedge clk)
begin
    if(!reset)
    begin
        soft_reset_0 <= 0;
        out_fifo_0_counter <= 0;
    end

    else if(vld_out_0)
    begin
        soft_reset_0 <= 0;
        out_fifo_0_counter <= 0;
    end

    else if(read_enb_0)
    begin
        soft_reset_0 <= 0;
        out_fifo_0_counter <= 0;
    end

    else if(count_0)
    begin
        out_fifo_0_counter <= 0;
        soft_reset_0 <= 1;
    end

    else
    begin
        out_fifo_0_counter <= out_fifo_0_counter + 1;
        soft_reset_0 <= 0;
    end
end


// FIFO 1 counter logic

always @(posedge clk)
begin
    if(!reset)
    begin
        soft_reset_1 <= 0;
        out_fifo_1_counter <= 0;
    end

    else if(vld_out_1)
    begin
        soft_reset_1 <= 0;
        out_fifo_1_counter <= 0;
    end

    else if(read_enb_1)
    begin
        soft_reset_1 <= 0;
        out_fifo_1_counter <= 0;
    end

    else if(count_1)
    begin
        out_fifo_1_counter <= 0;
        soft_reset_1 <= 1;
    end

    else
    begin
        out_fifo_1_counter <= out_fifo_1_counter + 1;
        soft_reset_1 <= 0;
    end
end


// FIFO 2 counter logic

always @(posedge clk)
begin
    if(!reset)
    begin
        soft_reset_2 <= 0;
        out_fifo_2_counter <= 0;
    end

    else if(vld_out_2)
    begin
        soft_reset_2 <= 0;
        out_fifo_2_counter <= 0;
    end

    else if(read_enb_2)
    begin
        soft_reset_2 <= 0;
        out_fifo_2_counter <= 0;
    end

    else if(count_2)
    begin
        out_fifo_2_counter <= 0;
        soft_reset_2 <= 1;
    end

    else
    begin
        out_fifo_2_counter <= out_fifo_2_counter + 1;
        soft_reset_2 <= 0;
    end
end

endmodule

SYNCHRONIZER/tb_synchronizer_router.v
`timescale 1ns/1ps

module tb_synchronizer_router;

reg clk;
reg reset;

reg detect_add;
reg write_enb_reg;
reg [1:0] data_in;

reg read_enb_0, read_enb_1, read_enb_2;
reg empty_0, empty_1, empty_2;
reg full_0, full_1, full_2;

wire vld_out_0, vld_out_1, vld_out_2;
wire [2:0] write_enb;
wire fifo_full;
wire soft_reset_0, soft_reset_1, soft_reset_2;

// DUT
synchronizer_router dut(
    .detect_add(detect_add),
    .data_in(data_in),
    .write_enb_reg(write_enb_reg),
    .clk(clk),
    .reset(reset),
    .vld_out_0(vld_out_0),
    .vld_out_1(vld_out_1),
    .vld_out_2(vld_out_2),
    .read_enb_0(read_enb_0),
    .read_enb_1(read_enb_1),
    .read_enb_2(read_enb_2),
    .write_enb(write_enb),
    .fifo_full(fifo_full),
    .empty_0(empty_0),
    .empty_1(empty_1),
    .empty_2(empty_2),
    .soft_reset_0(soft_reset_0),
    .soft_reset_1(soft_reset_1),
    .soft_reset_2(soft_reset_2),
    .full_0(full_0),
    .full_1(full_1),
    .full_2(full_2)
);

// clock
always #5 clk = ~clk;

// waveform
initial begin
    $dumpfile("sync_router.vcd");
    $dumpvars(0,tb_synchronizer_router);
end


initial begin
    clk = 0;
    reset = 0;

    detect_add = 0;
    write_enb_reg = 0;
    data_in = 2'b00;

    read_enb_0 = 0;
    read_enb_1 = 0;
    read_enb_2 = 0;

    empty_0 = 1;
    empty_1 = 1;
    empty_2 = 1;

    full_0 = 0;
    full_1 = 0;
    full_2 = 0;

    // -------------------------------------------------
    // TEST 1 : RESET
    // -------------------------------------------------
    #15 reset = 1;
    $display("Reset released");

    // -------------------------------------------------
    // TEST 2 : Address capture FIFO0
    // -------------------------------------------------
    #10 detect_add = 1;
    data_in = 2'b00;
    #10 detect_add = 0;

    write_enb_reg = 1;
    #20;

    // -------------------------------------------------
    // TEST 3 : Address capture FIFO1
    // -------------------------------------------------
    write_enb_reg = 0;
    #10 detect_add = 1;
    data_in = 2'b01;
    #10 detect_add = 0;

    write_enb_reg = 1;
    #20;

    // -------------------------------------------------
    // TEST 4 : Address capture FIFO2
    // -------------------------------------------------
    write_enb_reg = 0;
    #10 detect_add = 1;
    data_in = 2'b10;
    #10 detect_add = 0;

    write_enb_reg = 1;
    #20;

    // -------------------------------------------------
    // TEST 5 : FIFO FULL detection
    // -------------------------------------------------
    full_2 = 1;
    #20;
    full_2 = 0;

    // -------------------------------------------------
    // TEST 6 : VALID OUTPUT generation
    // -------------------------------------------------
    empty_0 = 0;
    empty_1 = 0;
    empty_2 = 0;
    #20;

    empty_0 = 1;
    empty_1 = 1;
    empty_2 = 1;

    // -------------------------------------------------
    // TEST 7 : SOFT RESET generation
    // no read enable for ~30 cycles
    // -------------------------------------------------
    data_in = 2'b00;
    detect_add = 1;
    #10 detect_add = 0;

    repeat(35) #10;

    // -------------------------------------------------
    // TEST 8 : Read enable clears counter
    // -------------------------------------------------
    read_enb_0 = 1;
    #20;
    read_enb_0 = 0;

    repeat(10) #10;

    // -------------------------------------------------
    $display("Simulation finished");
    #20 $finish;
end

endmodule

SYNCHRONIZER/sync_router.vcd
$date
	Fri Mar 06 12:42:45 2026
$end
$version
	Icarus Verilog
$end
$timescale
	1ps
$end
$scope module tb_synchronizer_router $end
$var wire 3 ! write_enb [2:0] $end
$var wire 1 " vld_out_2 $end
$var wire 1 # vld_out_1 $end
$var wire 1 $ vld_out_0 $end
$var wire 1 % soft_reset_2 $end
$var wire 1 & soft_reset_1 $end
$var wire 1 ' soft_reset_0 $end
$var wire 1 ( fifo_full $end
$var reg 1 ) clk $end
$var reg 2 * data_in [1:0] $end
$var reg 1 + detect_add $end
$var reg 1 , empty_0 $end
$var reg 1 - empty_1 $end
$var reg 1 . empty_2 $end
$var reg 1 / full_0 $end
$var reg 1 0 full_1 $end
$var reg 1 1 full_2 $end
$var reg 1 2 read_enb_0 $end
$var reg 1 3 read_enb_1 $end
$var reg 1 4 read_enb_2 $end
$var reg 1 5 reset $end
$var reg 1 6 write_enb_reg $end
$scope module dut $end
$var wire 1 ) clk $end
$var wire 2 7 data_in [1:0] $end
$var wire 1 + detect_add $end
$var wire 1 , empty_0 $end
$var wire 1 - empty_1 $end
$var wire 1 . empty_2 $end
$var wire 1 / full_0 $end
$var wire 1 0 full_1 $end
$var wire 1 1 full_2 $end
$var wire 1 2 read_enb_0 $end
$var wire 1 3 read_enb_1 $end
$var wire 1 4 read_enb_2 $end
$var wire 1 5 reset $end
$var wire 1 $ vld_out_0 $end
$var wire 1 # vld_out_1 $end
$var wire 1 " vld_out_2 $end
$var wire 1 6 write_enb_reg $end
$var wire 1 8 count_2 $end
$var wire 1 9 count_1 $end
$var wire 1 : count_0 $end
$var reg 2 ; addr_data [1:0] $end
$var reg 1 ( fifo_full $end
$var reg 7 < out_fifo_0_counter [6:0] $end
$var reg 7 = out_fifo_1_counter [6:0] $end
$var reg 7 > out_fifo_2_counter [6:0] $end
$var reg 1 ' soft_reset_0 $end
$var reg 1 & soft_reset_1 $end
$var reg 1 % soft_reset_2 $end
$var reg 3 ? write_enb [2:0] $end
$upscope $end
$upscope $end
$enddefinitions $end
$comment Show the parameter values. $end
$dumpall
$end
#0
$dumpvars
b0 ?
bx >
bx =
bx <
bx ;
x:
x9
x8
b0 7
06
05
04
03
02
01
00
0/
1.
1-
1,
0+
b0 *
0)
0(
x'
x&
x%
0$
0#
0"
b0 !
$end
#5000
0:
09
08
b0 ;
b0 <
0'
b0 =
0&
b0 >
0%
1)
#10000
0)
#15000
b1 >
b1 =
b1 <
1)
15
#20000
0)
#25000
b10 <
b10 =
b10 >
1)
1+
#30000
0)
#35000
b11 >
b11 =
b11 <
b1 !
b1 ?
1)
16
0+
#40000
0)
#45000
b100 <
b100 =
b100 >
1)
#50000
0)
#55000
b101 >
b101 =
b101 <
b0 !
b0 ?
1)
06
#60000
0)
#65000
b1 ;
b110 <
b110 =
b110 >
1)
b1 *
b1 7
1+
#70000
0)
#75000
b111 >
b111 =
b111 <
b10 !
b10 ?
1)
16
0+
#80000
0)
#85000
b1000 <
b1000 =
b1000 >
1)
#90000
0)
#95000
b1001 >
b1001 =
b1001 <
b0 !
b0 ?
1)
06
#100000
0)
#105000
b10 ;
b1010 <
b1010 =
b1010 >
1)
b10 *
b10 7
1+
#110000
0)
#115000
b1011 >
b1011 =
b1011 <
b100 !
b100 ?
1)
16
0+
#120000
0)
#125000
b1100 <
b1100 =
b1100 >
1)
#130000
0)
#135000
b1101 >
b1101 =
b1101 <
1(
1)
11
#140000
0)
#145000
b1110 <
b1110 =
b1110 >
1)
#150000
0)
#155000
b0 >
b0 =
b0 <
1"
1#
1$
0(
1)
0.
0-
0,
01
#160000
0)
#165000
1)
#170000
0)
#175000
b1 !
b1 ?
b1 >
b1 =
b1 <
b0 ;
0"
0#
0$
1)
1+
b0 *
b0 7
1.
1-
1,
#180000
0)
#185000
b10 <
b10 =
b10 >
1)
0+
#190000
0)
#195000
b11 >
b11 =
b11 <
1)
#200000
0)
#205000
b100 <
b100 =
b100 >
1)
#210000
0)
#215000
b101 >
b101 =
b101 <
1)
#220000
0)
#225000
b110 <
b110 =
b110 >
1)
#230000
0)
#235000
b111 >
b111 =
b111 <
1)
#240000
0)
#245000
b1000 <
b1000 =
b1000 >
1)
#250000
0)
#255000
b1001 >
b1001 =
b1001 <
1)
#260000
0)
#265000
b1010 <
b1010 =
b1010 >
1)
#270000
0)
#275000
b1011 >
b1011 =
b1011 <
1)
#280000
0)
#285000
b1100 <
b1100 =
b1100 >
1)
#290000
0)
#295000
b1101 >
b1101 =
b1101 <
1)
#300000
0)
#305000
b1110 <
b1110 =
b1110 >
1)
#310000
0)
#315000
b1111 >
b1111 =
b1111 <
1)
#320000
0)
#325000
b10000 <
b10000 =
b10000 >
1)
#330000
0)
#335000
b10001 >
b10001 =
b10001 <
1)
#340000
0)
#345000
b10010 <
b10010 =
b10010 >
1)
#350000
0)
#355000
b10011 >
b10011 =
b10011 <
1)
#360000
0)
#365000
b10100 <
b10100 =
b10100 >
1)
#370000
0)
#375000
b10101 >
b10101 =
b10101 <
1)
#380000
0)
#385000
b10110 <
b10110 =
b10110 >
1)
#390000
0)
#395000
b10111 >
b10111 =
b10111 <
1)
#400000
0)
#405000
b11000 <
b11000 =
b11000 >
1)
#410000
0)
#415000
b11001 >
b11001 =
b11001 <
1)
#420000
0)
#425000
b11010 <
b11010 =
b11010 >
1)
#430000
0)
#435000
b11011 >
b11011 =
b11011 <
1)
#440000
0)
#445000
b11100 <
b11100 =
b11100 >
1)
#450000
0)
#455000
18
19
1:
b11101 >
b11101 =
b11101 <
1)
#460000
0)
#465000
0:
09
08
1'
b0 <
1&
b0 =
1%
b0 >
1)
#470000
0)
#475000
0%
b1 >
0&
b1 =
0'
b1 <
1)
#480000
0)
#485000
b10 <
b10 =
b10 >
1)
#490000
0)
#495000
b11 >
b11 =
b11 <
1)
#500000
0)
#505000
b100 <
b100 =
b100 >
1)
#510000
0)
#515000
b101 >
b101 =
b101 <
1)
#520000
0)
#525000
b110 <
b110 =
b110 >
1)
#530000
0)
#535000
b111 >
b111 =
b0 <
1)
12
#540000
0)
#545000
b1000 =
b1000 >
1)
#550000
0)
#555000
b1001 >
b1001 =
b1 <
1)
02
#560000
0)
#565000
b10 <
b1010 =
b1010 >
1)
#570000
0)
#575000
b1011 >
b1011 =
b11 <
1)
#580000
0)
#585000
b100 <
b1100 =
b1100 >
1)
#590000
0)
#595000
b1101 >
b1101 =
b101 <
1)
#600000
0)
#605000
b110 <
b1110 =
b1110 >
1)
#610000
0)
#615000
b1111 >
b1111 =
b111 <
1)
#620000
0)
#625000
b1000 <
b10000 =
b10000 >
1)
#630000
0)
#635000
b10001 >
b10001 =
b1001 <
1)
#640000
0)
#645000
b1010 <
b10010 =
b10010 >
1)
#650000
0)
#655000
b10011 >
b10011 =
b1011 <
1)
#660000
0)
#665000
b1100 <
b10100 =
b10100 >
1)
#670000
0)
#675000
b10101 >
b10101 =
b1101 <
1)
