FSM/fsm_router_controller.v
// fsmm

module fsm_router_controller(clk,reset,pkt_valid,busy,parity_done,data_in,
soft_reset_0,soft_reset_1,soft_reset_2,fifo_full,low_pkt_valid,fifo_empty_0,
fifo_empty_1,fifo_empty_2,detect_add,ld_state,laf_state,full_state,write_enb_reg,
rst_int_reg,lfd_state);

// declaring the input and output ports

input clk,reset,pkt_valid,parity_done,soft_reset_0,soft_reset_1,soft_reset_2,
fifo_full,low_pkt_valid,fifo_empty_0,fifo_empty_1,fifo_empty_2;

input [1:0] data_in;

output detect_add,ld_state,laf_state,full_state,rst_int_reg,lfd_state;
output busy,write_enb_reg;


// creating internal register for present state,next state regs declarations

parameter DECODE_ADDRESS=3'b000,LOAD_FIRST_DATA=3'b001,WAIT_TILL_EMPTY=3'b010,
LOAD_DATA=3'b011,FIFO_FULL_STATE=3'b100,LOAD_AFTER_FULL=3'b101,
LOAD_PARITY=3'b110,CHECK_PARITY_ERROR=3'b111;

reg [1:0] addr_data;
reg [2:0] present,next;


// storing detecting the destination_address_signal

always@(*)
begin
    if(!reset)
        addr_data<=0;
    else
    begin
        if(detect_add)
            addr_data <= data_in;
    end
end


// sequential logic for present state

always@(posedge clk)
begin
    if(!reset)
        present<=DECODE_ADDRESS;
    else if(soft_reset_0 || soft_reset_1 || soft_reset_2)
        present<=DECODE_ADDRESS;
    else
        present<=next;
end


// combinational logic for next state

always@(*)
begin
    case(present)

    DECODE_ADDRESS:
    begin
        if((pkt_valid && addr_data == 2'd0 && fifo_empty_0) ||
           (pkt_valid && addr_data == 2'd1 && fifo_empty_1) ||
           (pkt_valid && addr_data == 2'd2 && fifo_empty_2))
            next=LOAD_FIRST_DATA;

        else if((pkt_valid && addr_data == 2'd0 && (!fifo_empty_0)) ||
                (pkt_valid && addr_data == 2'd1 && (!fifo_empty_1)) ||
                (pkt_valid && addr_data == 2'd2 && (!fifo_empty_2)))
            next=WAIT_TILL_EMPTY;

        else
            next=DECODE_ADDRESS;
    end


    WAIT_TILL_EMPTY:
    begin
        if((addr_data == 2'd0 && fifo_empty_0) ||
           (addr_data == 2'd1 && fifo_empty_1) ||
           (addr_data == 2'd2 && fifo_empty_2))
            next=LOAD_FIRST_DATA;
        else
            next=WAIT_TILL_EMPTY;
    end


    LOAD_FIRST_DATA:
        next=LOAD_DATA;


    LOAD_DATA:
    begin
        if(fifo_full)
            next=FIFO_FULL_STATE;

        else if(!fifo_full && !pkt_valid)
            next=LOAD_PARITY;

        else
            next=LOAD_DATA;
    end


    FIFO_FULL_STATE:
    begin
        if(!fifo_full)
            next=LOAD_AFTER_FULL;
        else
            next=FIFO_FULL_STATE;
    end


    LOAD_AFTER_FULL:
    begin
        if(!parity_done && !low_pkt_valid)
            next=LOAD_DATA;

        else if(!parity_done && low_pkt_valid)
            next=LOAD_PARITY;

        else if(parity_done)
            next=DECODE_ADDRESS;
    end


    LOAD_PARITY:
        next=CHECK_PARITY_ERROR;


    CHECK_PARITY_ERROR:
    begin
        if(fifo_full)
            next=FIFO_FULL_STATE;
        else
            next=DECODE_ADDRESS;
    end


    default:
        next=DECODE_ADDRESS;

    endcase
end



// combinational logic for output
// busy is going to low at decode state and load state other states it was
// high bcaz it is not allowing new data from the source

assign busy = ((present == DECODE_ADDRESS) || (present == LOAD_DATA)) ? 1'b0 : 1'b1;

assign detect_add = (present == DECODE_ADDRESS) ? 1'b1 : 1'b0;
assign ld_state = (present == LOAD_DATA) ? 1'b1 : 1'b0;
assign laf_state = (present == LOAD_AFTER_FULL) ? 1'b1 : 1'b0;
assign full_state = (present == FIFO_FULL_STATE) ? 1'b1 : 1'b0;
assign lfd_state = (present == LOAD_FIRST_DATA) ? 1'b1 : 1'b0;
assign rst_int_reg = (present == CHECK_PARITY_ERROR) ? 1'b1 : 1'b0;


// write enb reg going tp high only in these state bcaz these stae have
// capable for sending payload and parity data to fifo when write enb reg is
// high then only we know which fifo desination.neccessary to send the data
// at he particular stae

assign write_enb_reg = ((present == LOAD_DATA) ||
                        (present == LOAD_PARITY) ||
                        (present == LOAD_AFTER_FULL)) ? 1'b1 : 1'b0;

endmodule

FSM/tb_fsm_router_controller.v
`timescale 1ns/1ps

module tb_fsm_router_controller;

reg clk;
reg reset;
reg pkt_valid;
reg parity_done;
reg fifo_full;
reg low_pkt_valid;
reg soft_reset_0, soft_reset_1, soft_reset_2;
reg fifo_empty_0, fifo_empty_1, fifo_empty_2;
reg [1:0] data_in;

wire detect_add, ld_state, laf_state, full_state, rst_int_reg, lfd_state;
wire busy, write_enb_reg;

// DUT
fsm_router_controller dut(
    .clk(clk),
    .reset(reset),
    .pkt_valid(pkt_valid),
    .busy(busy),
    .parity_done(parity_done),
    .data_in(data_in),
    .soft_reset_0(soft_reset_0),
    .soft_reset_1(soft_reset_1),
    .soft_reset_2(soft_reset_2),
    .fifo_full(fifo_full),
    .low_pkt_valid(low_pkt_valid),
    .fifo_empty_0(fifo_empty_0),
    .fifo_empty_1(fifo_empty_1),
    .fifo_empty_2(fifo_empty_2),
    .detect_add(detect_add),
    .ld_state(ld_state),
    .laf_state(laf_state),
    .full_state(full_state),
    .write_enb_reg(write_enb_reg),
    .rst_int_reg(rst_int_reg),
    .lfd_state(lfd_state)
);

// clock
always #5 clk = ~clk;

// waveform dump
initial begin
    $dumpfile("fsm_router.vcd");
    $dumpvars(0, tb_fsm_router_controller);
end

// helper task: idle
task idle;
begin
    pkt_valid = 0;
    parity_done = 0;
    fifo_full = 0;
    low_pkt_valid = 0;
    soft_reset_0 = 0;
    soft_reset_1 = 0;
    soft_reset_2 = 0;
    fifo_empty_0 = 1;
    fifo_empty_1 = 1;
    fifo_empty_2 = 1;
    data_in = 2'd0;
end
endtask

initial begin
    clk = 0;
    reset = 0;
    idle;

    // -----------------------------------------
    // TEST 1: RESET
    // -----------------------------------------
    #12;
    reset = 1;
    $display("TEST1: Reset released");

    // -----------------------------------------
    // TEST 2: Normal packet flow (FIFO empty)
    // DECODE -> LOAD_FIRST_DATA -> LOAD_DATA
    // -----------------------------------------
    data_in = 2'd0;     // destination FIFO0
    pkt_valid = 1;
    fifo_empty_0 = 1;

    #20; // should go to LOAD_FIRST_DATA
    #20; // should go to LOAD_DATA

    // payload cycles
    #20;
    #20;

    // -----------------------------------------
    // TEST 3: Parity arrival
    // LOAD_DATA -> LOAD_PARITY
    // -----------------------------------------
    pkt_valid = 0;  // parity byte phase
    #20;

    // -----------------------------------------
    // TEST 4: Parity check
    // LOAD_PARITY -> CHECK_PARITY_ERROR
    // -----------------------------------------
    parity_done = 1;
    #20;
    parity_done = 0;

    // -----------------------------------------
    // TEST 5: WAIT_TILL_EMPTY path
    // DECODE_ADDRESS -> WAIT_TILL_EMPTY
    // -----------------------------------------
    pkt_valid = 1;
    data_in = 2'd1;     // FIFO1
    fifo_empty_1 = 0;   // FIFO busy
    #20;

    // FIFO becomes empty
    fifo_empty_1 = 1;
    #20;

    // -----------------------------------------
    // TEST 6: FIFO FULL state
    // LOAD_DATA -> FIFO_FULL_STATE
    // -----------------------------------------
    data_in = 2'd2;
    pkt_valid = 1;
    fifo_empty_2 = 1;

    #20;
    fifo_full = 1;  // force full
    #20;

    // -----------------------------------------
    // TEST 7: LOAD_AFTER_FULL
    // -----------------------------------------
    fifo_full = 0;
    #20;

    // continue payload
    pkt_valid = 1;
    #20;

    // -----------------------------------------
    // TEST 8: LOAD_AFTER_FULL -> LOAD_PARITY
    // -----------------------------------------
    pkt_valid = 0;
    low_pkt_valid = 1;
    #20;

    // -----------------------------------------
    // TEST 9: Soft reset
    // -----------------------------------------
    soft_reset_0 = 1;
    #20;
    soft_reset_0 = 0;

    // -----------------------------------------
    // finish
    // -----------------------------------------
    #40;
    $display("All FSM edge cases simulated.");
    $finish;
end

endmodule

FSM/fsm_router.vcd
$date
	Fri Mar 06 12:24:16 2026
$end
$version
	Icarus Verilog
$end
$timescale
	1ps
$end
$scope module tb_fsm_router_controller $end
$var wire 1 ! write_enb_reg $end
$var wire 1 " rst_int_reg $end
$var wire 1 # lfd_state $end
$var wire 1 $ ld_state $end
$var wire 1 % laf_state $end
$var wire 1 & full_state $end
$var wire 1 ' detect_add $end
$var wire 1 ( busy $end
$var reg 1 ) clk $end
$var reg 2 * data_in [1:0] $end
$var reg 1 + fifo_empty_0 $end
$var reg 1 , fifo_empty_1 $end
$var reg 1 - fifo_empty_2 $end
$var reg 1 . fifo_full $end
$var reg 1 / low_pkt_valid $end
$var reg 1 0 parity_done $end
$var reg 1 1 pkt_valid $end
$var reg 1 2 reset $end
$var reg 1 3 soft_reset_0 $end
$var reg 1 4 soft_reset_1 $end
$var reg 1 5 soft_reset_2 $end
$scope module dut $end
$var wire 1 ) clk $end
$var wire 2 6 data_in [1:0] $end
$var wire 1 + fifo_empty_0 $end
$var wire 1 , fifo_empty_1 $end
$var wire 1 - fifo_empty_2 $end
$var wire 1 . fifo_full $end
$var wire 1 / low_pkt_valid $end
$var wire 1 0 parity_done $end
$var wire 1 1 pkt_valid $end
$var wire 1 2 reset $end
$var wire 1 3 soft_reset_0 $end
$var wire 1 4 soft_reset_1 $end
$var wire 1 5 soft_reset_2 $end
$var wire 1 ! write_enb_reg $end
$var wire 1 " rst_int_reg $end
$var wire 1 # lfd_state $end
$var wire 1 $ ld_state $end
$var wire 1 % laf_state $end
$var wire 1 & full_state $end
$var wire 1 ' detect_add $end
$var wire 1 ( busy $end
$var parameter 3 7 CHECK_PARITY_ERROR $end
$var parameter 3 8 DECODE_ADDRESS $end
$var parameter 3 9 FIFO_FULL_STATE $end
$var parameter 3 : LOAD_AFTER_FULL $end
$var parameter 3 ; LOAD_DATA $end
$var parameter 3 < LOAD_FIRST_DATA $end
$var parameter 3 = LOAD_PARITY $end
$var parameter 3 > WAIT_TILL_EMPTY $end
$var reg 2 ? addr_data [1:0] $end
$var reg 3 @ next [2:0] $end
$var reg 3 A present [2:0] $end
$upscope $end
$scope task idle $end
$upscope $end
$upscope $end
$enddefinitions $end
$comment Show the parameter values. $end
$dumpall
b10 >
b110 =
b1 <
b11 ;
b101 :
b100 9
b0 8
b111 7
$end
#0
$dumpvars
bx A
b0 @
b0 ?
b0 6
05
04
03
02
01
00
0/
0.
1-
1,
1+
b0 *
0)
x(
x'
x&
x%
x$
x#
x"
x!
$end
#5000
0!
0(
1'
0$
0%
0&
0#
0"
b0 A
1)
#10000
0)
#12000
b1 @
11
12
#15000
1(
b11 @
0'
1#
b1 A
1)
#20000
0)
#25000
1!
0(
1$
0#
b11 A
1)
#30000
0)
#35000
1)
#40000
0)
#45000
1)
#50000
0)
#55000
1)
#60000
0)
#65000
1)
#70000
0)
#75000
1)
#80000
0)
#85000
1)
#90000
0)
#92000
b110 @
01
#95000
1(
b111 @
0$
b110 A
1)
#100000
0)
#105000
0!
b0 @
1"
b111 A
1)
#110000
0)
#112000
10
#115000
0(
1'
0"
b0 A
1)
#120000
0)
#125000
1)
#130000
0)
#132000
b1 ?
b10 @
0,
b1 *
b1 6
11
00
#135000
1(
0'
b10 A
1)
#140000
0)
#145000
1)
#150000
0)
#152000
b1 @
1,
#155000
b11 @
1#
b1 A
1)
#160000
0)
#165000
1!
0(
1$
0#
b11 A
1)
#170000
0)
#172000
b10 *
b10 6
#175000
1)
#180000
0)
#185000
1)
#190000
0)
#192000
b100 @
1.
#195000
0!
1(
0$
1&
b100 A
1)
#200000
0)
#205000
1)
#210000
0)
#212000
b101 @
0.
#215000
1!
b11 @
1%
0&
b101 A
1)
#220000
0)
#225000
0(
1!
1$
0%
b11 A
1)
#230000
0)
#235000
1)
#240000
0)
#245000
1)
#250000
0)
#252000
b110 @
1/
01
#255000
1(
b111 @
0$
b110 A
1)
#260000
0)
#265000
0!
b0 @
1"
b111 A
1)
#270000
0)
#272000
13
#275000
b10 ?
0(
1'
0"
b0 A
1)
#280000
0)
#285000
1)
#290000
0)
#292000
03
